{
  "progress": {
    "мһҲлӢӨ": {
      "status": "reviewing",
      "stability": 0.049999999999999996,
      "difficulty": 0.3,
      "nextReview": 1775637208114,
      "lastReview": 1775633608114,
      "reps": 3,
      "lapses": 0,
      "streak": 3
    },
    "мҲҳмІ©": {
      "status": "reviewing",
      "stability": 0.008333333333333333,
      "difficulty": 0.3,
      "nextReview": 1775634215009,
      "lastReview": 1775633615009,
      "reps": 2,
      "lapses": 0,
      "streak": 2
    },
    "лғүмһҘкі ": {
      "status": "reviewing",
      "stability": 0.008333333333333333,
      "difficulty": 0.3,
      "nextReview": 1775634218720,
      "lastReview": 1775633618720,
      "reps": 2,
      "lapses": 0,
      "streak": 2
    },
    "м№ңкө¬": {
      "status": "reviewing",
      "stability": 0.008333333333333333,
      "difficulty": 0.3,
      "nextReview": 1775634224313,
      "lastReview": 1775633624313,
      "reps": 2,
      "lapses": 0,
      "streak": 2
    },
    "м ҒлӢӨ": {
      "status": "reviewing",
      "stability": 0.008333333333333333,
      "difficulty": 0.3,
      "nextReview": 1775634220587,
      "lastReview": 1775633620587,
      "reps": 2,
      "lapses": 0,
      "streak": 2
    },
    "мҳҶ": {
      "status": "reviewing",
      "stability": 0.008333333333333333,
      "difficulty": 0.3,
      "nextReview": 1775634222257,
      "lastReview": 1775633622257,
      "reps": 2,
      "lapses": 0,
      "streak": 2
    },
    "нҒ¬лӢӨ": {
      "status": "reviewing",
      "stability": 0.008333333333333333,
      "difficulty": 0.3,
      "nextReview": 1775634216975,
      "lastReview": 1775633616975,
      "reps": 2,
      "lapses": 0,
      "streak": 2
    },
    "мһҗ": {
      "status": "reviewing",
      "stability": 0.008333333333333333,
      "difficulty": 0.3,
      "nextReview": 1775634225328,
      "lastReview": 1775633625328,
      "reps": 2,
      "lapses": 0,
      "streak": 2
    },
    "мһ‘лӢӨ": {
      "status": "reviewing",
      "stability": 0.008333333333333333,
      "difficulty": 0.3,
      "nextReview": 1775634211298,
      "lastReview": 1775633611298,
      "reps": 2,
      "lapses": 0,
      "streak": 2
    },
    "мқҳмһҗ": {
      "status": "reviewing",
      "stability": 0.008333333333333333,
      "difficulty": 0.3,
      "nextReview": 1775634223479,
      "lastReview": 1775633623479,
      "reps": 2,
      "lapses": 0,
      "streak": 2
    },
    "м–ҙлҠҗ": {
      "status": "reviewing",
      "stability": 0.008333333333333333,
      "difficulty": 0.3,
      "nextReview": 1775635407149,
      "lastReview": 1775634807149,
      "reps": 2,
      "lapses": 0,
      "streak": 2
    },
    "м•Ҳл…•~": {
      "status": "reviewing",
      "stability": 0.008333333333333333,
      "difficulty": 0.3,
      "nextReview": 1775635412460,
      "lastReview": 1775634812460,
      "reps": 2,
      "lapses": 0,
      "streak": 2
    },
    "м Җ": {
      "status": "reviewing",
      "stability": 0.008333333333333333,
      "difficulty": 0.3,
      "nextReview": 1775635410610,
      "lastReview": 1775634810610,
      "reps": 2,
      "lapses": 0,
      "streak": 2
    },
    "м•Ҳл…•н•ҳм„ёмҡ”?": {
      "status": "reviewing",
      "stability": 0.07261718748009417,
      "difficulty": 0.15299999999999997,
      "nextReview": 1775649758678.9983,
      "lastReview": 1775643484554,
      "reps": 4,
      "lapses": 0,
      "streak": 4
    },
    "м„ мғқлӢҳ": {
      "status": "reviewing",
      "stability": 0.05725681344986836,
      "difficulty": 0.22999999999999998,
      "nextReview": 1775648393123.6821,
      "lastReview": 1775643446135,
      "reps": 3,
      "lapses": 0,
      "streak": 3
    },
    "мҳҒкөӯ": {
      "status": "reviewing",
      "stability": 0.05725681344986836,
      "difficulty": 0.22999999999999998,
      "nextReview": 1775648365613.6821,
      "lastReview": 1775643418625,
      "reps": 3,
      "lapses": 0,
      "streak": 3
    },
    "лҹ¬мӢңм•„": {
      "status": "reviewing",
      "stability": 0.008333333333333333,
      "difficulty": 0.3,
      "nextReview": 1775635421483,
      "lastReview": 1775634821483,
      "reps": 2,
      "lapses": 0,
      "streak": 2
    },
    "~м”Ё": {
      "status": "reviewing",
      "stability": 0.05725681344986836,
      "difficulty": 0.22999999999999998,
      "nextReview": 1775648368614.6821,
      "lastReview": 1775643421626,
      "reps": 3,
      "lapses": 0,
      "streak": 3
    },
    "мқҖн–үмӣҗ": {
      "status": "reviewing",
      "stability": 0.05725681344986836,
      "difficulty": 0.22999999999999998,
      "nextReview": 1775648417336.6821,
      "lastReview": 1775643470348,
      "reps": 3,
      "lapses": 0,
      "streak": 3
    },
    "н•ҷмғқ": {
      "status": "reviewing",
      "stability": 0.008333333333333333,
      "difficulty": 0.3,
      "nextReview": 1775635419083,
      "lastReview": 1775634819083,
      "reps": 2,
      "lapses": 0,
      "streak": 2
    },
    "мӨ‘көӯ": {
      "status": "reviewing",
      "stability": 0.008333333333333333,
      "difficulty": 0.3,
      "nextReview": 1775635776660,
      "lastReview": 1775635176660,
      "reps": 2,
      "lapses": 0,
      "streak": 2
    },
    "мқјліё": {
      "status": "reviewing",
      "stability": 0.005725681344986835,
      "difficulty": 0.22999999999999998,
      "nextReview": 1775643899587.8682,
      "lastReview": 1775643404889,
      "reps": 2,
      "lapses": 0,
      "streak": 2
    },
    "мӮ¬лһҢ": {
      "status": "reviewing",
      "stability": 0.005725681344986835,
      "difficulty": 0.22999999999999998,
      "nextReview": 1775643917506.8682,
      "lastReview": 1775643422808,
      "reps": 2,
      "lapses": 0,
      "streak": 2
    },
    "м ң": {
      "status": "reviewing",
      "stability": 0.005725681344986835,
      "difficulty": 0.22999999999999998,
      "nextReview": 1775643945822.8682,
      "lastReview": 1775643451124,
      "reps": 2,
      "lapses": 0,
      "streak": 2
    },
    "мқҙлӢӨ/мһ…лӢҲлӢӨ": {
      "status": "reviewing",
      "stability": 0.007566520704259415,
      "difficulty": 0.15299999999999997,
      "nextReview": 1775644103254.389,
      "lastReview": 1775643449507,
      "reps": 3,
      "lapses": 0,
      "streak": 3
    },
    "лҜёкөӯ": {
      "status": "learning",
      "stability": 0.0008333333333333334,
      "difficulty": 0.3,
      "nextReview": 1775634898926,
      "lastReview": 1775634838926,
      "reps": 1,
      "lapses": 0,
      "streak": 1
    },
    "к·ёл ҮмҠөлӢҲк№Ң?": {
      "status": "learning",
      "stability": 0.0008333333333333334,
      "difficulty": 0.3,
      "nextReview": 1775635136059,
      "lastReview": 1775635076059,
      "reps": 1,
      "lapses": 0,
      "streak": 1
    },
    "мәҗлӮҳлӢӨ": {
      "status": "learning",
      "stability": 0.0008333333333333334,
      "difficulty": 0.3,
      "nextReview": 1775634913542,
      "lastReview": 1775634853542,
      "reps": 1,
      "lapses": 0,
      "streak": 1
    },
    "м„ұ": {
      "status": "reviewing",
      "stability": 0.005725681344986835,
      "difficulty": 0.22999999999999998,
      "nextReview": 1775643907450.8682,
      "lastReview": 1775643412752,
      "reps": 2,
      "lapses": 0,
      "streak": 2
    },
    "мқҳмӮ¬": {
      "status": "learning",
      "stability": 0.0008333333333333334,
      "difficulty": 0.3,
      "nextReview": 1775634920342,
      "lastReview": 1775634860342,
      "reps": 1,
      "lapses": 0,
      "streak": 1
    },
    "нғңкөӯ": {
      "status": "reviewing",
      "stability": 0.05725681344986836,
      "difficulty": 0.22999999999999998,
      "nextReview": 1775648402364.6821,
      "lastReview": 1775643455376,
      "reps": 3,
      "lapses": 0,
      "streak": 3
    },
    "лҸ…мқј": {
      "status": "learning",
      "stability": 0.0008333333333333334,
      "difficulty": 0.3,
      "nextReview": 1775635161852,
      "lastReview": 1775635101852,
      "reps": 1,
      "lapses": 0,
      "streak": 1
    },
    "лҲ„кө¬": {
      "status": "reviewing",
      "stability": 0.005725681344986835,
      "difficulty": 0.22999999999999998,
      "nextReview": 1775643977223.8682,
      "lastReview": 1775643482525,
      "reps": 2,
      "lapses": 0,
      "streak": 2
    },
    "н•ңкөӯ": {
      "status": "learning",
      "stability": 0.0008333333333333334,
      "difficulty": 0.3,
      "nextReview": 1775634946213,
      "lastReview": 1775634886213,
      "reps": 1,
      "lapses": 0,
      "streak": 1
    },
    "к°ҖмҲҳ": {
      "status": "reviewing",
      "stability": 0.005725681344986835,
      "difficulty": 0.22999999999999998,
      "nextReview": 1775643974672.8682,
      "lastReview": 1775643479974,
      "reps": 2,
      "lapses": 0,
      "streak": 2
    },
    "мІҳмқҢ лөҷкІ мҠөлӢҲлӢӨ": {
      "status": "learning",
      "stability": 0.0008333333333333334,
      "difficulty": 0.3,
      "nextReview": 1775635216831,
      "lastReview": 1775635156831,
      "reps": 1,
      "lapses": 0,
      "streak": 1
    },
    "лҢҖн•ҷмғқ": {
      "status": "reviewing",
      "stability": 0.008333333333333333,
      "difficulty": 0.3,
      "nextReview": 1775635775071,
      "lastReview": 1775635175071,
      "reps": 2,
      "lapses": 0,
      "streak": 2
    },
    "нҡҢмӮ¬мӣҗ": {
      "status": "reviewing",
      "stability": 0.005725681344986835,
      "difficulty": 0.22999999999999998,
      "nextReview": 1775643973586.8682,
      "lastReview": 1775643478888,
      "reps": 2,
      "lapses": 0,
      "streak": 2
    },
    "ліҖнҳёмӮ¬": {
      "status": "learning",
      "stability": 0.0008333333333333334,
      "difficulty": 0.3,
      "nextReview": 1775635016376,
      "lastReview": 1775634956376,
      "reps": 1,
      "lapses": 0,
      "streak": 1
    },
    "л°ҳк°‘лӢӨ": {
      "status": "reviewing",
      "stability": 0.005725681344986835,
      "difficulty": 0.22999999999999998,
      "nextReview": 1775643919807.8682,
      "lastReview": 1775643425109,
      "reps": 2,
      "lapses": 0,
      "streak": 2
    },
    "кё°мһҗ": {
      "status": "reviewing",
      "stability": 0.005725681344986835,
      "difficulty": 0.22999999999999998,
      "nextReview": 1775643911374.8682,
      "lastReview": 1775643416676,
      "reps": 2,
      "lapses": 0,
      "streak": 2
    },
    "лӮҳлқј": {
      "status": "learning",
      "stability": 0.0008333333333333334,
      "difficulty": 0.3,
      "nextReview": 1775635075309,
      "lastReview": 1775635015309,
      "reps": 1,
      "lapses": 0,
      "streak": 1
    },
    "м•Ҳл…•н•ҳмӢӯлӢҲк№Ң?": {
      "status": "reviewing",
      "stability": 0.008177151429259415,
      "difficulty": 0.15299999999999997,
      "nextReview": 1775644180200.8835,
      "lastReview": 1775643473695,
      "reps": 3,
      "lapses": 0,
      "streak": 3
    },
    "л„Ө": {
      "status": "reviewing",
      "stability": 0.005725681344986835,
      "difficulty": 0.22999999999999998,
      "nextReview": 1775643981025.8682,
      "lastReview": 1775643486327,
      "reps": 2,
      "lapses": 0,
      "streak": 2
    },
    "кІҪм°°": {
      "status": "learning",
      "stability": 0.0008333333333333334,
      "difficulty": 0.3,
      "nextReview": 1775635203889,
      "lastReview": 1775635143889,
      "reps": 1,
      "lapses": 0,
      "streak": 1
    },
    "Г¬ВһВҲГ«ВӢВӨ": {
      "status": "reviewing",
      "correctCount": 3,
      "nextReview": 1775637208114,
      "lastReview": 1775633608114
    },
    "Г¬ВҲВҳГ¬ВІВ©": {
      "status": "reviewing",
      "correctCount": 2,
      "nextReview": 1775634215009,
      "lastReview": 1775633615009
    },
    "Г«ВғВүГ¬ВһВҘГӘВіВ ": {
      "status": "reviewing",
      "correctCount": 2,
      "nextReview": 1775634218720,
      "lastReview": 1775633618720
    },
    "Г¬В№ВңГӘВөВ¬": {
      "status": "reviewing",
      "correctCount": 2,
      "nextReview": 1775634224313,
      "lastReview": 1775633624313
    },
    "Г¬В ВҒГ«ВӢВӨ": {
      "status": "reviewing",
      "correctCount": 2,
      "nextReview": 1775634220587,
      "lastReview": 1775633620587
    },
    "Г¬ВҳВҶ": {
      "status": "reviewing",
      "correctCount": 2,
      "nextReview": 1775634222257,
      "lastReview": 1775633622257
    },
    "ГӯВҒВ¬Г«ВӢВӨ": {
      "status": "reviewing",
      "correctCount": 2,
      "nextReview": 1775634216975,
      "lastReview": 1775633616975
    },
    "Г¬ВһВҗ": {
      "status": "reviewing",
      "correctCount": 2,
      "nextReview": 1775634225328,
      "lastReview": 1775633625328
    },
    "Г¬ВһВ‘Г«ВӢВӨ": {
      "status": "reviewing",
      "correctCount": 2,
      "nextReview": 1775634211298,
      "lastReview": 1775633611298
    },
    "Г¬ВқВҳГ¬ВһВҗ": {
      "status": "reviewing",
      "correctCount": 2,
      "nextReview": 1775634223479,
      "lastReview": 1775633623479
    },
    "Г¬В–ВҙГ«ВҠВҗ": {
      "status": "reviewing",
      "correctCount": 2,
      "nextReview": 1775635407149,
      "lastReview": 1775634807149
    },
    "Г¬В•ВҲГ«В…В•~": {
      "status": "reviewing",
      "correctCount": 2,
      "nextReview": 1775635412460,
      "lastReview": 1775634812460
    },
    "Г¬В ВҖ": {
      "status": "reviewing",
      "correctCount": 2,
      "nextReview": 1775635410610,
      "lastReview": 1775634810610
    },
    "Г¬В•ВҲГ«В…В•ГӯВ•ВҳГ¬В„ВёГ¬ВҡВ”?": {
      "status": "reviewing",
      "correctCount": 2,
      "nextReview": 1775635426417,
      "lastReview": 1775634826417
    },
    "Г¬В„В Г¬ВғВқГ«ВӢВҳ": {
      "status": "reviewing",
      "correctCount": 2,
      "nextReview": 1775635423210,
      "lastReview": 1775634823210
    },
    "Г¬ВҳВҒГӘВөВӯ": {
      "status": "reviewing",
      "correctCount": 2,
      "nextReview": 1775635423958,
      "lastReview": 1775634823958
    },
    "Г«ВҹВ¬Г¬ВӢВңГ¬В•В„": {
      "status": "reviewing",
      "correctCount": 2,
      "nextReview": 1775635421483,
      "lastReview": 1775634821483
    },
    "~Г¬В”ВЁ": {
      "status": "reviewing",
      "correctCount": 2,
      "nextReview": 1775635422209,
      "lastReview": 1775634822209
    },
    "Г¬ВқВҖГӯВ–ВүГ¬ВӣВҗ": {
      "status": "reviewing",
      "correctCount": 2,
      "nextReview": 1775635416687,
      "lastReview": 1775634816687
    },
    "ГӯВ•ВҷГ¬ВғВқ": {
      "status": "reviewing",
      "correctCount": 2,
      "nextReview": 1775635419083,
      "lastReview": 1775634819083
    },
    "Г¬ВӨВ‘ГӘВөВӯ": {
      "status": "reviewing",
      "correctCount": 2,
      "nextReview": 1775635776660,
      "lastReview": 1775635176660
    },
    "Г¬ВқВјГ«ВіВё": {
      "status": "learning",
      "correctCount": 1,
      "nextReview": 1775634890811,
      "lastReview": 1775634830811
    },
    "Г¬ВӮВ¬Г«ВһВҢ": {
      "status": "learning",
      "correctCount": 1,
      "nextReview": 1775634892442,
      "lastReview": 1775634832442
    },
    "Г¬В Вң": {
      "status": "learning",
      "correctCount": 1,
      "nextReview": 1775634894968,
      "lastReview": 1775634834968
    },
    "Г¬ВқВҙГ«ВӢВӨ/Г¬ВһВ…Г«ВӢВҲГ«ВӢВӨ": {
      "status": "learning",
      "correctCount": 1,
      "nextReview": 1775634897403,
      "lastReview": 1775634837403
    },
    "Г«ВҜВёГӘВөВӯ": {
      "status": "learning",
      "correctCount": 1,
      "nextReview": 1775634898926,
      "lastReview": 1775634838926
    },
    "ГӘВ·ВёГ«В ВҮГ¬ВҠВөГ«ВӢВҲГӘВ№ВҢ?": {
      "status": "learning",
      "correctCount": 1,
      "nextReview": 1775635136059,
      "lastReview": 1775635076059
    },
    "Г¬ВәВҗГ«ВӮВҳГ«ВӢВӨ": {
      "status": "learning",
      "correctCount": 1,
      "nextReview": 1775634913542,
      "lastReview": 1775634853542
    },
    "Г¬В„Вұ": {
      "status": "learning",
      "correctCount": 1,
      "nextReview": 1775635142782,
      "lastReview": 1775635082782
    },
    "Г¬ВқВҳГ¬ВӮВ¬": {
      "status": "learning",
      "correctCount": 1,
      "nextReview": 1775634920342,
      "lastReview": 1775634860342
    },
    "ГӯВғВңГӘВөВӯ": {
      "status": "reviewing",
      "correctCount": 2,
      "nextReview": 1775635773272,
      "lastReview": 1775635173272
    },
    "Г«ВҸВ…Г¬ВқВј": {
      "status": "learning",
      "correctCount": 1,
      "nextReview": 1775635161852,
      "lastReview": 1775635101852
    },
    "Г«ВҲВ„ГӘВөВ¬": {
      "status": "learning",
      "correctCount": 1,
      "nextReview": 1775634943959,
      "lastReview": 1775634883959
    },
    "ГӯВ•ВңГӘВөВӯ": {
      "status": "learning",
      "correctCount": 1,
      "nextReview": 1775634946213,
      "lastReview": 1775634886213
    },
    "ГӘВ°ВҖГ¬ВҲВҳ": {
      "status": "learning",
      "correctCount": 1,
      "nextReview": 1775635207142,
      "lastReview": 1775635147142
    },
    "Г¬ВІВҳГ¬ВқВҢ Г«ВөВҷГӘВІВ Г¬ВҠВөГ«ВӢВҲГ«ВӢВӨ": {
      "status": "learning",
      "correctCount": 1,
      "nextReview": 1775635216831,
      "lastReview": 1775635156831
    },
    "Г«ВҢВҖГӯВ•ВҷГ¬ВғВқ": {
      "status": "reviewing",
      "correctCount": 2,
      "nextReview": 1775635775071,
      "lastReview": 1775635175071
    },
    "ГӯВҡВҢГ¬ВӮВ¬Г¬ВӣВҗ": {
      "status": "learning",
      "correctCount": 1,
      "nextReview": 1775635012025,
      "lastReview": 1775634952025
    },
    "Г«ВіВҖГӯВҳВёГ¬ВӮВ¬": {
      "status": "learning",
      "correctCount": 1,
      "nextReview": 1775635016376,
      "lastReview": 1775634956376
    },
    "Г«В°ВҳГӘВ°В‘Г«ВӢВӨ": {
      "status": "learning",
      "correctCount": 1,
      "nextReview": 1775635021078,
      "lastReview": 1775634961078
    },
    "ГӘВёВ°Г¬ВһВҗ": {
      "status": "learning",
      "correctCount": 1,
      "nextReview": 1775635223049,
      "lastReview": 1775635163049
    },
    "Г«ВӮВҳГ«ВқВј": {
      "status": "learning",
      "correctCount": 1,
      "nextReview": 1775635075309,
      "lastReview": 1775635015309
    },
    "Г¬В•ВҲГ«В…В•ГӯВ•ВҳГ¬ВӢВӯГ«ВӢВҲГӘВ№ВҢ?": {
      "status": "learning",
      "correctCount": 1,
      "nextReview": 1775635121340,
      "lastReview": 1775635061340
    },
    "Г«В„ВӨ": {
      "status": "learning",
      "correctCount": 1,
      "nextReview": 1775635122890,
      "lastReview": 1775635062890
    },
    "ГӘВІВҪГ¬В°В°": {
      "status": "learning",
      "correctCount": 1,
      "nextReview": 1775635203889,
      "lastReview": 1775635143889
    },
    "_ch0": {
      "newIndex": 12
    }
  },
  "history": [
    {
      "date": "2026-04-08",
      "chapter": 2,
      "total": 14,
      "timestamp": 1775633459811
    },
    {
      "date": "2026-04-08",
      "chapter": 1,
      "total": 11,
      "timestamp": 1775633601529
    },
    {
      "date": "2026-04-08",
      "chapter": 0,
      "total": 11,
      "timestamp": 1775633625328
    },
    {
      "date": "2026-04-08",
      "chapter": 1,
      "total": 45,
      "timestamp": 1775635163050
    }
  ]
}